webnoti/__init__.py
webnoti/encryption.py
webnoti/notification.py
webnoti/utils.py
python_webnoti-0.4.1.dist-info/LICENSE
python_webnoti-0.4.1.dist-info/METADATA
python_webnoti-0.4.1.dist-info/WHEEL
python_webnoti-0.4.1.dist-info/top_level.txt
python_webnoti-0.4.1.dist-info/RECORD
