Metadata-Version: 2.1
Name: python-webnoti
Version: 0.4.1
Summary: Easy-to-use Web Push Notification Library
Home-page: https://github.com/puilp0502/python-webnoti
Author: Frank Yang
Author-email: puilp0502@gmail.com
License: MIT
Keywords: web push notification
Platform: UNKNOWN
Classifier: Development Status :: 3 - Alpha
Classifier: Intended Audience :: Developers
Classifier: Topic :: Internet :: WWW/HTTP
Classifier: Topic :: Software Development :: Libraries
Classifier: License :: OSI Approved :: MIT License
Classifier: Programming Language :: Python :: 3
Classifier: Programming Language :: Python :: 3.3
Classifier: Programming Language :: Python :: 3.4
Classifier: Programming Language :: Python :: 3.5
Requires-Dist: cryptography (>=2.5)
Requires-Dist: PyJWT
Requires-Dist: requests
